setup.py
FirstPackage/__init__.py
FirstPackage.egg-info/PKG-INFO
FirstPackage.egg-info/SOURCES.txt
FirstPackage.egg-info/dependency_links.txt
FirstPackage.egg-info/not-zip-safe
FirstPackage.egg-info/top_level.txt