Metadata-Version: 1.0
Name: FirstPackage
Version: 0.1
Summary: My First Package
Home-page: UNKNOWN
Author: Pupun
Author-email: demon.saturn@gmail.com
License: Pupun
Platform: UNKNOWN
